oidc/__init__.py
oidc/apps.py
oidc/configure.html
oidc/constants.py
oidc/provider.py
oidc/views.py
oidc/oidc/configure.html
oidc/template/oidc/configure.html
oidc/templates/oidc/configure.html
kkauth_oidc-0.0.14.dist-info/LICENSE
kkauth_oidc-0.0.14.dist-info/METADATA
kkauth_oidc-0.0.14.dist-info/WHEEL
kkauth_oidc-0.0.14.dist-info/entry_points.txt
kkauth_oidc-0.0.14.dist-info/top_level.txt
kkauth_oidc-0.0.14.dist-info/RECORD
